{
  "date": "2022-05-13",
  "pics": [
    {
      "imageUrl": "https://i.redd.it/drc39voxo2z81.png",
      "postTitle": "This Vaguely Threatening Advert",
      "postUrl": "https://www.reddit.com/r/CrappyDesign/comments/uo57li/this_vaguely_threatening_advert/",
      "op": "Posted by: /u/CircuitBreakerD"
    },
    {
      "imageUrl": "https://i.redd.it/zdf09xk6spy81.jpg",
      "postTitle": "PIC",
      "postUrl": "https://www.reddit.com/r/nocontextpics/comments/umsxjk/pic/",
      "op": "Posted by: /u/morganmonroe81"
    },
    {
      "imageUrl": "https://i.redd.it/4evgzgjslwx81.jpg",
      "postTitle": "I Dont Think The Sign Meant That..............",
      "postUrl": "https://www.reddit.com/r/Funnypics/comments/ujup3n/i_dont_think_the_sign_meant_that/",
      "op": "Posted by: /u/OldMan3212"
    },
    {
      "imageUrl": "https://i.redd.it/atnzff1bi2y81.jpg",
      "postTitle": "PIC",
      "postUrl": "https://www.reddit.com/r/nocontextpics/comments/ukf04y/pic/",
      "op": "Posted by: /u/Aggravating-Deal-260"
    },
    {
      "imageUrl": "https://i.imgur.com/ikvrS3X.gif",
      "postTitle": "MRW when my childs first word is fuck.",
      "postUrl": "https://www.reddit.com/r/reactiongifs/comments/uk193j/mrw_when_my_childs_first_word_is_fuck/",
      "op": "Posted by: /u/Akuma2890"
    },
    {
      "imageUrl": "https://i.redd.it/k2xcft5j5gy81.jpg",
      "postTitle": "Russias ambassador to Poland, Sergey Andreev, covered with red paint in Warsaw",
      "postUrl": "https://www.reddit.com/r/pics/comments/ulqh61/russias_ambassador_to_poland_sergey_andreev/",
      "op": "Posted by: /u/OofOofOofgang"
    },
    {
      "imageUrl": "https://i.redd.it/6kd4gdkgkwy81.jpg",
      "postTitle": "stop",
      "postUrl": "https://www.reddit.com/r/funnysigns/comments/unijj5/stop/",
      "op": "Posted by: /u/Lmanwell23"
    },
    {
      "imageUrl": "https://i.redd.it/wogjydaucxx81.png",
      "postTitle": "I was told I look like a Mexican Michael Scott",
      "postUrl": "https://www.reddit.com/r/pics/comments/ujxz09/i_was_told_i_look_like_a_mexican_michael_scott/",
      "op": "Posted by: /u/FarazR90"
    },
    {
      "imageUrl": "https://i.redd.it/w3i7y6d7jvy81.png",
      "postTitle": "Making your cigarette disposal boxes out of flammable material",
      "postUrl": "https://www.reddit.com/r/CrappyDesign/comments/undx9r/making_your_cigarette_disposal_boxes_out_of/",
      "op": "Posted by: /u/philman132"
    },
    {
      "imageUrl": "https://i.redd.it/lwvy08kokmy81.jpg",
      "postTitle": "hmmm",
      "postUrl": "https://www.reddit.com/r/hmmm/comments/umfiei/hmmm/",
      "op": "Posted by: /u/justNabves"
    },
    {
      "imageUrl": "https://i.redd.it/yfkk7xnrwxy81.jpg",
      "postTitle": "hmmm",
      "postUrl": "https://www.reddit.com/r/hmmm/comments/uno8gt/hmmm/",
      "op": "Posted by: /u/x2py"
    },
    {
      "imageUrl": "https://i.redd.it/aqd0wbav6ky81.jpg",
      "postTitle": "Spotted in my North Carolina town OC",
      "postUrl": "https://www.reddit.com/r/pics/comments/um7wp8/spotted_in_my_north_carolina_town_oc/",
      "op": "Posted by: /u/thepsycholeech"
    },
    {
      "imageUrl": "https://i.redd.it/vkc1wxr9eyx81.jpg",
      "postTitle": "Old one that makes me laff",
      "postUrl": "https://www.reddit.com/r/funnysigns/comments/ukgigb/old_one_that_makes_me_laff/",
      "op": "Posted by: /u/notcharldeon"
    },
    {
      "imageUrl": "https://i.imgur.com/RP0lWBx.jpg",
      "postTitle": "PIC",
      "postUrl": "https://www.reddit.com/r/nocontextpics/comments/une9j3/pic/",
      "op": "Posted by: /u/CausticDux"
    },
    {
      "imageUrl": "https://i.redd.it/qpjjmklsuwx81.jpg",
      "postTitle": "Parked my truck next to this car today",
      "postUrl": "https://www.reddit.com/r/funny/comments/ujvrx7/parked_my_truck_next_to_this_car_today/",
      "op": "Posted by: /u/RuralRangerMA"
    },
    {
      "imageUrl": "https://i.redd.it/6eljgl8r0ey81.png",
      "postTitle": "I would KILL for free college",
      "postUrl": "https://www.reddit.com/r/funny/comments/ulk8lm/i_would_kill_for_free_college/",
      "op": "Posted by: /u/Miles_the_new_kid"
    },
    {
      "imageUrl": "https://i.redd.it/emjn4q1oi2y81.jpg",
      "postTitle": "Egg",
      "postUrl": "https://www.reddit.com/r/IDAP/comments/ukf1f4/egg/",
      "op": "Posted by: /u/akulosaari"
    },
    {
      "imageUrl": "https://i.redd.it/f0euhqpufxy81.jpg",
      "postTitle": "Cotton Cat",
      "postUrl": "https://www.reddit.com/r/Eyebleach/comments/unmdke/cotton_cat/",
      "op": "Posted by: /u/sh0tgunben"
    },
    {
      "imageUrl": "https://i.redd.it/0p2znayfety81.gif",
      "postTitle": "Must memorize",
      "postUrl": "https://www.reddit.com/r/memes/comments/un5tjw/must_memorize/",
      "op": "Posted by: /u/Barry_Mckockiner12"
    },
    {
      "imageUrl": "https://i.redd.it/y6hwr0rmz2z81.jpg",
      "postTitle": "Medical examination",
      "postUrl": "https://www.reddit.com/r/funny/comments/uo6naw/medical_examination/",
      "op": "Posted by: /u/SrGrafo"
    },
    {
      "imageUrl": "https://i.redd.it/wqnfzqiou7y81.gif",
      "postTitle": "Finally",
      "postUrl": "https://www.reddit.com/r/memes/comments/ukxngi/finally/",
      "op": "Posted by: /u/Barry_Mckockiner12"
    },
    {
      "imageUrl": "https://i.redd.it/fulkc358duy81.jpg",
      "postTitle": "My oil painting of Taco Bell",
      "postUrl": "https://www.reddit.com/r/pics/comments/un8uwv/my_oil_painting_of_taco_bell/",
      "op": "Posted by: /u/NoahVerrier"
    },
    {
      "imageUrl": "https://i.redd.it/micjvy88xty81.gif",
      "postTitle": "MRW I keep hearing that Netflix wants to add commercials to their platform.",
      "postUrl": "https://www.reddit.com/r/reactiongifs/comments/un7c31/mrw_i_keep_hearing_that_netflix_wants_to_add/",
      "op": "Posted by: /u/_Sophacouch_"
    },
    {
      "imageUrl": "https://i.redd.it/31ef1fd49ny81.jpg",
      "postTitle": "Spotted in Hamburg, Germany",
      "postUrl": "https://www.reddit.com/r/streetart/comments/umhsnz/spotted_in_hamburg_germany/",
      "op": "Posted by: /u/Feelinara1992"
    },
    {
      "imageUrl": "https://i.redd.it/i72x92l4djy81.jpg",
      "postTitle": "PIC",
      "postUrl": "https://www.reddit.com/r/nocontextpics/comments/um4let/pic/",
      "op": "Posted by: /u/TheGuvnor247"
    },
    {
      "imageUrl": "https://i.redd.it/o3an2z7b92z81.jpg",
      "postTitle": "Beware of demons.",
      "postUrl": "https://www.reddit.com/r/Funnypics/comments/uo39i5/beware_of_demons/",
      "op": "Posted by: /u/groomleader"
    },
    {
      "imageUrl": "https://i.redd.it/rwqyfwka0ny81.jpg",
      "postTitle": "Somewhere in Alsace, me, acrylic, 2022",
      "postUrl": "https://www.reddit.com/r/Art/comments/umgwth/somewhere_in_alsace_me_acrylic_2022/",
      "op": "Posted by: /u/Anastasia_Trusova"
    },
    {
      "imageUrl": "https://i.redd.it/cj68zc26g0y81.jpg",
      "postTitle": "Quackasaurus, Me, Digital, 2022",
      "postUrl": "https://www.reddit.com/r/Art/comments/uk8ipm/quackasaurus_me_digital_2022/",
      "op": "Posted by: /u/TalSh"
    },
    {
      "imageUrl": "https://i.imgur.com/C2Siknx.jpg",
      "postTitle": "PIC",
      "postUrl": "https://www.reddit.com/r/nocontextpics/comments/unzm4v/pic/",
      "op": "Posted by: /u/My_Bird_Buddy"
    },
    {
      "imageUrl": "https://i.redd.it/tww7cxtg4ay81.jpg",
      "postTitle": "Art by me",
      "postUrl": "https://www.reddit.com/r/IDAP/comments/ul5haj/art_by_me/",
      "op": "Posted by: /u/StarvingArtist2000"
    },
    {
      "imageUrl": "https://i.redd.it/49oll8jmc3y81.gif",
      "postTitle": "MRW the waiter asks if I enjoyed my chicken nuggets with mac N cheese that I ordered off the kids menu at my business lunch",
      "postUrl": "https://www.reddit.com/r/reactiongifs/comments/ukig8x/mrw_the_waiter_asks_if_i_enjoyed_my_chicken/",
      "op": "Posted by: /u/ThEhIsO8730"
    },
    {
      "imageUrl": "https://i.redd.it/p03wlgeax1y81.jpg",
      "postTitle": "OC Biblically Accurate pick up line",
      "postUrl": "https://www.reddit.com/r/funny/comments/ukcr07/oc_biblically_accurate_pick_up_line/",
      "op": "Posted by: /u/colmscomics"
    },
    {
      "imageUrl": "https://cdna.artstation.com/p/assets/images/images/048/706/252/large/sigita-luse-aimonl-variants-ar-vairak-gaismus.jpg",
      "postTitle": "rImaginaryArchers Elf Bowman by Sigita Luse",
      "postUrl": "https://www.reddit.com/r/ImaginaryBestOf/comments/ukfv5n/rimaginaryarchers_elf_bowman_by_sigita_luse/",
      "op": "Posted by: /u/Lol33ta"
    },
    {
      "imageUrl": "https://i.redd.it/jmyu54bjhvx81.gif",
      "postTitle": "Cat.",
      "postUrl": "https://www.reddit.com/r/CatsStandingUp/comments/uk3j8r/cat/",
      "op": "Posted by: /u/kavyaharlalka"
    },
    {
      "imageUrl": "https://i.redd.it/ufjgc784nhy81.jpg",
      "postTitle": "Great advertising.",
      "postUrl": "https://www.reddit.com/r/Funnypics/comments/ulwxoc/great_advertising/",
      "op": "Posted by: /u/groomleader"
    },
    {
      "imageUrl": "https://i.redd.it/y8q7josyawx81.jpg",
      "postTitle": "Fart squirrels.",
      "postUrl": "https://www.reddit.com/r/funnysigns/comments/ujte7b/fart_squirrels/",
      "op": "Posted by: /u/GryphonSK"
    },
    {
      "imageUrl": "https://i.redd.it/lfrlyiz6f9y81.jpg",
      "postTitle": "PIC",
      "postUrl": "https://www.reddit.com/r/nocontextpics/comments/ul2jqp/pic/",
      "op": "Posted by: /u/Racingamer145"
    },
    {
      "imageUrl": "https://i.redd.it/hvhag705dxy81.jpg",
      "postTitle": "front camera selfie at my local deli",
      "postUrl": "https://www.reddit.com/r/IDAP/comments/unm2gi/front_camera_selfie_at_my_local_deli/",
      "op": "Posted by: /u/tibularity"
    },
    {
      "imageUrl": "https://i.redd.it/vtmg17e364y81.gif",
      "postTitle": "MRW Im in my late 30s, its 1045 at night, and the opening act is still on stage",
      "postUrl": "https://www.reddit.com/r/reactiongifs/comments/uklq6b/mrw_im_in_my_late_30s_its_1045_at_night_and_the/",
      "op": "Posted by: /u/ThEhIsO8730"
    },
    {
      "imageUrl": "https://i.redd.it/d05kdiqdeny81.gif",
      "postTitle": "MRW I get that 2hr raise",
      "postUrl": "https://www.reddit.com/r/reactiongifs/comments/umidsz/mrw_i_get_that_2hr_raise/",
      "op": "Posted by: /u/unknown_human"
    },
    {
      "imageUrl": "https://i.redd.it/hcozpyemfiy81.jpg",
      "postTitle": "Perfect Blue fanart",
      "postUrl": "https://www.reddit.com/r/IDAP/comments/um0hjf/perfect_blue_fanart/",
      "op": "Posted by: /u/akulosaari"
    },
    {
      "imageUrl": "https://cdnb.artstation.com/p/assets/images/images/047/085/939/large/ognjen-sporin-bunny-final.jpg",
      "postTitle": "rImaginaryPortals Beast of Caerbannog by Ognjen Sporin",
      "postUrl": "https://www.reddit.com/r/ImaginaryBestOf/comments/ul10lc/rimaginaryportals_beast_of_caerbannog_by_ognjen/",
      "op": "Posted by: /u/Lol33ta"
    },
    {
      "imageUrl": "https://i.redd.it/fs3da4bx2cy81.jpg",
      "postTitle": "hmmm",
      "postUrl": "https://www.reddit.com/r/hmmm/comments/uldmm8/hmmm/",
      "op": "Posted by: /u/SalazarRED"
    },
    {
      "imageUrl": "https://i.redd.it/ecx6od1xacy81.png",
      "postTitle": "Girl with a futuristic steel earring, Me, Digital, 2021",
      "postUrl": "https://www.reddit.com/r/Art/comments/uleib6/girl_with_a_futuristic_steel_earring_me_digital/",
      "op": "Posted by: /u/rubios-workshop"
    },
    {
      "imageUrl": "https://i.redd.it/xsc1wh59vux81.jpg",
      "postTitle": "PIC",
      "postUrl": "https://www.reddit.com/r/nocontextpics/comments/ujn70v/pic/",
      "op": "Posted by: /u/Dhorlin"
    },
    {
      "imageUrl": "https://i.redd.it/slu6aqoxhvx81.jpg",
      "postTitle": "I painted Barbara and Adam Maitland from Beetlejuice",
      "postUrl": "https://www.reddit.com/r/IDAP/comments/ujpu9h/i_painted_barbara_and_adam_maitland_from/",
      "op": "Posted by: /u/DanniWho"
    },
    {
      "imageUrl": "https://i.imgur.com/jjmq6wq.jpg",
      "postTitle": "Damn near broke my ankle at the bottom of these steps",
      "postUrl": "https://www.reddit.com/r/CrappyDesign/comments/ul2n05/damn_near_broke_my_ankle_at_the_bottom_of_these/",
      "op": "Posted by: /u/vaskemaskine"
    },
    {
      "imageUrl": "https://i.redd.it/lrf61rsj8gy81.gif",
      "postTitle": "MRW my ultra conservative boss wants to talk about politics",
      "postUrl": "https://www.reddit.com/r/reactiongifs/comments/ulqsyh/mrw_my_ultra_conservative_boss_wants_to_talk/",
      "op": "Posted by: /u/palmerry"
    },
    {
      "imageUrl": "https://i.redd.it/u30yu667z1z81.png",
      "postTitle": "gains baby",
      "postUrl": "https://www.reddit.com/r/memes/comments/uo20pj/gains_baby/",
      "op": "Posted by: /u/Raso82"
    },
    {
      "imageUrl": "https://i.redd.it/h61y3y39s3z81.jpg",
      "postTitle": "Graffiti from 2020 pandemic about lack of govt support for frontline workers, SlaveNationArt",
      "postUrl": "https://www.reddit.com/r/streetart/comments/uoa0vv/graffiti_from_2020_pandemic_about_lack_of_govt/",
      "op": "Posted by: /u/SlaveNationArt22"
    },
    {
      "imageUrl": "https://i.redd.it/33h6rbhn3jy81.jpg",
      "postTitle": "Roevwade",
      "postUrl": "https://www.reddit.com/r/streetart/comments/um3ho7/roevwade/",
      "op": "Posted by: /u/smollshr00m"
    },
    {
      "imageUrl": "https://i.redd.it/mnc09suysny81.gif",
      "postTitle": "At least you tried",
      "postUrl": "https://www.reddit.com/r/memes/comments/umk38q/at_least_you_tried/",
      "op": "Posted by: /u/Vesto241"
    },
    {
      "imageUrl": "https://i.redd.it/50pm85uvzey81.jpg",
      "postTitle": "And hes keeping It Under His Collar.....",
      "postUrl": "https://www.reddit.com/r/Funnypics/comments/ulmvz7/and_hes_keeping_it_under_his_collar/",
      "op": "Posted by: /u/OldMan3212"
    },
    {
      "imageUrl": "https://i.redd.it/xpcddgld5ay81.jpg",
      "postTitle": "Help the planet and eat a Billionaire.",
      "postUrl": "https://www.reddit.com/r/streetart/comments/ul5l0k/help_the_planet_and_eat_a_billionaire/",
      "op": "Posted by: /u/SlaveNationArt22"
    },
    {
      "imageUrl": "https://i.redd.it/4kylthuecxy81.jpg",
      "postTitle": "Today I saw the David by Michelangelo. My mother made sure to take some photos.",
      "postUrl": "https://www.reddit.com/r/pics/comments/unm040/today_i_saw_the_david_by_michelangelo_my_mother/",
      "op": "Posted by: /u/nlderek"
    },
    {
      "imageUrl": "https://i.redd.it/mmj3lriew7y81.gif",
      "postTitle": "Spring, Me, Digital, 2022",
      "postUrl": "https://www.reddit.com/r/Art/comments/ukxsse/spring_me_digital_2022/",
      "op": "Posted by: /u/Nimmerdar"
    },
    {
      "imageUrl": "https://i.imgur.com/6zuddxq.jpg",
      "postTitle": "Dear Algebra",
      "postUrl": "https://www.reddit.com/r/funnysigns/comments/ul6e93/dear_algebra/",
      "op": "Posted by: /u/mikeymiggz"
    },
    {
      "imageUrl": "https://i.redd.it/y4ewkik5yty81.jpg",
      "postTitle": "Lo que lloran los muertos, Me, Photo, 2021",
      "postUrl": "https://www.reddit.com/r/Art/comments/un7fgb/lo_que_lloran_los_muertos_me_photo_2021/",
      "op": "Posted by: /u/Spectro510"
    },
    {
      "imageUrl": "https://i.redd.it/inxhesprwxy81.jpg",
      "postTitle": "Family at the basketball stadium, me, oils, 2022",
      "postUrl": "https://www.reddit.com/r/Art/comments/uno8jf/family_at_the_basketball_stadium_me_oils_2022/",
      "op": "Posted by: /u/davidrm_cuen"
    },
    {
      "imageUrl": "https://i.redd.it/kgoayzi3uxx81.jpg",
      "postTitle": "Cheesecake bandage looks like a gaping wound",
      "postUrl": "https://www.reddit.com/r/CrappyDesign/comments/ujzxqy/cheesecake_bandage_looks_like_a_gaping_wound/",
      "op": "Posted by: /u/PhantaVal"
    },
    {
      "imageUrl": "https://i.redd.it/otvjol1ea9y81.gif",
      "postTitle": "The Darwin Incident",
      "postUrl": "https://www.reddit.com/r/memes/comments/ul20xa/the_darwin_incident/",
      "op": "Posted by: /u/nechdoesntno"
    },
    {
      "imageUrl": "https://i.redd.it/rdhw2iu819y81.png",
      "postTitle": "Cat.",
      "postUrl": "https://www.reddit.com/r/CatsStandingUp/comments/ul2xzu/cat/",
      "op": "Posted by: /u/pockets_of_fingers"
    },
    {
      "imageUrl": "https://i.redd.it/r5sy4hmbf2z81.png",
      "postTitle": "A piece I did last year",
      "postUrl": "https://www.reddit.com/r/IDAP/comments/uo3zyt/a_piece_i_did_last_year/",
      "op": "Posted by: /u/art-of-pepeti"
    },
    {
      "imageUrl": "https://i.redd.it/6p6yb715fyx81.jpg",
      "postTitle": "PIC",
      "postUrl": "https://www.reddit.com/r/nocontextpics/comments/uk2434/pic/",
      "op": "Posted by: /u/Mario_lib"
    },
    {
      "imageUrl": "https://i.redd.it/guyu2lzcliy81.jpg",
      "postTitle": "hmmm",
      "postUrl": "https://www.reddit.com/r/hmmm/comments/um17li/hmmm/",
      "op": "Posted by: /u/Foodie4910"
    },
    {
      "imageUrl": "https://i.redd.it/wtjqn1edixx81.jpg",
      "postTitle": "GOP, me, tempera, 2022",
      "postUrl": "https://www.reddit.com/r/Art/comments/ujymes/gop_me_tempera_2022/",
      "op": "Posted by: /u/severedfinger"
    },
    {
      "imageUrl": "https://i.redd.it/uiz4w68jaay81.jpg",
      "postTitle": "OC My brother got my mom this gift for Mothers Day",
      "postUrl": "https://www.reddit.com/r/pics/comments/ul671z/oc_my_brother_got_my_mom_this_gift_for_mothers_day/",
      "op": "Posted by: /u/thereal_omegavince"
    },
    {
      "imageUrl": "https://i.redd.it/obwljnfolwx81.jpg",
      "postTitle": "Very Well Worded I Think",
      "postUrl": "https://www.reddit.com/r/Funnypics/comments/ujuolf/very_well_worded_i_think/",
      "op": "Posted by: /u/OldMan3212"
    },
    {
      "imageUrl": "https://i.redd.it/u0ctoxl361y81.png",
      "postTitle": "Adorable little boi",
      "postUrl": "https://www.reddit.com/r/Eyebleach/comments/ukai1x/adorable_little_boi/",
      "op": "Posted by: /u/Aztery"
    },
    {
      "imageUrl": "https://i.redd.it/y7q7799yjpy81.jpg",
      "postTitle": "This stairway has a surprise step",
      "postUrl": "https://www.reddit.com/r/CrappyDesign/comments/umrvcf/this_stairway_has_a_surprise_step/",
      "op": "Posted by: /u/TeresaKitsu"
    },
    {
      "imageUrl": "https://i.redd.it/wq8s2wxjhby81.jpg",
      "postTitle": "Beyond 24-7",
      "postUrl": "https://www.reddit.com/r/Funnypics/comments/ulb8cx/beyond_247/",
      "op": "Posted by: /u/groomleader"
    },
    {
      "imageUrl": "https://i.redd.it/oos0bf7efgy81.jpg",
      "postTitle": "Cat.",
      "postUrl": "https://www.reddit.com/r/CatsStandingUp/comments/ulrkp3/cat/",
      "op": "Posted by: /u/FuriouslyChonky"
    },
    {
      "imageUrl": "https://i.redd.it/mwt633bi79y81.jpg",
      "postTitle": "Carpe Die",
      "postUrl": "https://www.reddit.com/r/Funnypics/comments/ul1pdb/carpe_die/",
      "op": "Posted by: /u/LichtenbergFigyur"
    },
    {
      "imageUrl": "https://i.redd.it/tghjma3dncy81.jpg",
      "postTitle": "I wanna know who did this",
      "postUrl": "https://www.reddit.com/r/funnysigns/comments/ulfnhs/i_wanna_know_who_did_this/",
      "op": "Posted by: /u/Internetboy5434"
    },
    {
      "imageUrl": "https://i.redd.it/6wgg5fa4rxy81.jpg",
      "postTitle": "Outkast mural in Atlanta, GA. Seems to be very well maintained",
      "postUrl": "https://www.reddit.com/r/streetart/comments/unnmps/outkast_mural_in_atlanta_ga_seems_to_be_very_well/",
      "op": "Posted by: /u/cinematic99"
    },
    {
      "imageUrl": "https://i.redd.it/1pq50u9acfy81.jpg",
      "postTitle": "billboard subvertising Southampton UK by SlaveNationArt... fuck Piers",
      "postUrl": "https://www.reddit.com/r/streetart/comments/ulntdl/billboard_subvertising_southampton_uk_by/",
      "op": "Posted by: /u/SlaveNationArt22"
    },
    {
      "imageUrl": "https://i.redd.it/vy9zmw3wwny81.jpg",
      "postTitle": "I must be extremely wise then",
      "postUrl": "https://www.reddit.com/r/funnysigns/comments/umkket/i_must_be_extremely_wise_then/",
      "op": "Posted by: /u/Pandafour20"
    },
    {
      "imageUrl": "https://i.redd.it/di05q1nvqqy81.jpg",
      "postTitle": "Everyone kept hitting their heads as they walked down my stairs, so I hung a sign as a warning.",
      "postUrl": "https://www.reddit.com/r/funny/comments/umwzom/everyone_kept_hitting_their_heads_as_they_walked/",
      "op": "Posted by: /u/hot_controller"
    },
    {
      "imageUrl": "https://i.imgur.com/cdveooY.gif",
      "postTitle": "MRW Im playing competitive shooters in my mid-30s and the random teens Im playing with complement me on how Im doing",
      "postUrl": "https://www.reddit.com/r/reactiongifs/comments/unzlw3/mrw_im_playing_competitive_shooters_in_my_mid30s/",
      "op": "Posted by: /u/PapaNixon"
    },
    {
      "imageUrl": "https://cdna.artstation.com/p/assets/images/images/048/684/070/large/max-suleimanov-dv-167.jpg",
      "postTitle": "rImaginaryArchitecture Pavilion by Max Suleimanov",
      "postUrl": "https://www.reddit.com/r/ImaginaryBestOf/comments/ujorpo/rimaginaryarchitecture_pavilion_by_max_suleimanov/",
      "op": "Posted by: /u/Lol33ta"
    },
    {
      "imageUrl": "https://i.redd.it/hp0gtdgxqpy81.jpg",
      "postTitle": "Well, I think its a sign.",
      "postUrl": "https://www.reddit.com/r/funnysigns/comments/un8jec/well_i_think_its_a_sign/",
      "op": "Posted by: /u/Forward-Stock-1893"
    },
    {
      "imageUrl": "https://i.redd.it/g6ax6oylrwy81.jpg",
      "postTitle": "Poster found in PDX",
      "postUrl": "https://www.reddit.com/r/streetart/comments/unjfex/poster_found_in_pdx/",
      "op": "Posted by: /u/rabidbabe"
    },
    {
      "imageUrl": "https://i.imgur.com/fgLwFzB.gif",
      "postTitle": "Feelsbadman. Jpg",
      "postUrl": "https://www.reddit.com/r/memes/comments/ulmtkq/feelsbadman_jpg/",
      "op": "Posted by: /u/_The-Batman"
    },
    {
      "imageUrl": "https://i.redd.it/4zy7lee70ay81.gif",
      "postTitle": "MRW I do my first sit-up in 8 years and can feel the washboard abs forming under my layers of fat",
      "postUrl": "https://www.reddit.com/r/reactiongifs/comments/ul4yub/mrw_i_do_my_first_situp_in_8_years_and_can_feel/",
      "op": "Posted by: /u/ThEhIsO8730"
    },
    {
      "imageUrl": "https://i.redd.it/q0gpqgro45y81.jpg",
      "postTitle": "hmmm",
      "postUrl": "https://www.reddit.com/r/hmmm/comments/ukpfeo/hmmm/",
      "op": "Posted by: /u/TrumpsTinyChode"
    },
    {
      "imageUrl": "https://i.redd.it/d7bcvizrv1y81.jpg",
      "postTitle": "Panhandler, or maybe prostitute",
      "postUrl": "https://www.reddit.com/r/Funnypics/comments/ulfdnd/panhandler_or_maybe_prostitute/",
      "op": "Posted by: /u/nullterm"
    },
    {
      "imageUrl": "https://cdna.artstation.com/p/assets/images/images/048/540/268/large/longque-chen-vehicle-ex-copy-11.jpg",
      "postTitle": "rImaginaryVehicles Helicopter Rover by Longque Chen",
      "postUrl": "https://www.reddit.com/r/ImaginaryBestOf/comments/umj1nz/rimaginaryvehicles_helicopter_rover_by_longque/",
      "op": "Posted by: /u/Lol33ta"
    },
    {
      "imageUrl": "https://i.redd.it/vscfhxj2coy81.jpg",
      "postTitle": "Mona Lisa in my style",
      "postUrl": "https://www.reddit.com/r/IDAP/comments/ummgvf/mona_lisa_in_my_style/",
      "op": "Posted by: /u/art-of-pepeti"
    },
    {
      "imageUrl": "https://i.redd.it/9oovrt49h4z81.jpg",
      "postTitle": "My nephew snuck safety goggles to his school photo.",
      "postUrl": "https://www.reddit.com/r/pics/comments/uod7k1/my_nephew_snuck_safety_goggles_to_his_school_photo/",
      "op": "Posted by: /u/IansjonesPGH"
    },
    {
      "imageUrl": "https://i.redd.it/3fudwmsppwy81.gif",
      "postTitle": "Luxury living",
      "postUrl": "https://www.reddit.com/r/memes/comments/unjbqt/luxury_living/",
      "op": "Posted by: /u/johnlen1n"
    },
    {
      "imageUrl": "https://i.redd.it/67wzckujs0z81.jpg",
      "postTitle": "Letz go",
      "postUrl": "https://www.reddit.com/r/funnysigns/comments/unxrve/letz_go/",
      "op": "Posted by: /u/UNIQUE_9212"
    },
    {
      "imageUrl": "https://cdnb.artstation.com/p/assets/images/images/048/533/103/large/fran-fdez-frontier-spot-iii-final.jpg",
      "postTitle": "rImaginaryBeasts Parrotsaurus by Fran Fdez",
      "postUrl": "https://www.reddit.com/r/ImaginaryBestOf/comments/uo1nk8/rimaginarybeasts_parrotsaurus_by_fran_fdez/",
      "op": "Posted by: /u/Lol33ta"
    },
    {
      "imageUrl": "https://i.redd.it/6yrtbi5844y81.jpg",
      "postTitle": "Critical Race Theory, Jonathan Harris, Oil, 2021",
      "postUrl": "https://www.reddit.com/r/Art/comments/uklhze/critical_race_theory_jonathan_harris_oil_2021/",
      "op": "Posted by: /u/Fancy-Benefit3344"
    },
    {
      "imageUrl": "https://i.redd.it/uq27bkzv68y81.jpg",
      "postTitle": "hmmm",
      "postUrl": "https://www.reddit.com/r/hmmm/comments/ukyism/hmmm/",
      "op": "Posted by: /u/Metalloid_Emon"
    },
    {
      "imageUrl": "https://i.redd.it/2pr44z8g6fy81.jpg",
      "postTitle": "hmmm",
      "postUrl": "https://www.reddit.com/r/hmmm/comments/ulnda9/hmmm/",
      "op": "Posted by: /u/x2py"
    },
    {
      "imageUrl": "https://i.redd.it/eojkcwgz9yx81.jpg",
      "postTitle": "hmmm",
      "postUrl": "https://www.reddit.com/r/hmmm/comments/uk1lep/hmmm/",
      "op": "Posted by: /u/LexTalioniss"
    },
    {
      "imageUrl": "https://i.imgur.com/PkOgkjC.jpg",
      "postTitle": "This is the picture Amazon sent my BIL to say the packages were delivered to a family member directly",
      "postUrl": "https://www.reddit.com/r/funny/comments/unkqkr/this_is_the_picture_amazon_sent_my_bil_to_say_the/",
      "op": "Posted by: /u/mayorofutopia"
    },
    {
      "imageUrl": "https://cdnb.artstation.com/p/assets/images/images/048/884/137/large/yuumei-wenqing-yan-in-search-of-flight-2-post.jpg",
      "postTitle": "rImaginaryAngels Simulacra of Flight by Yuumei Wenqing Yan",
      "postUrl": "https://www.reddit.com/r/ImaginaryBestOf/comments/unawdi/rimaginaryangels_simulacra_of_flight_by_yuumei/",
      "op": "Posted by: /u/Lol33ta"
    }
  ],
  "preview": "https://i.redd.it/otvjol1ea9y81.gif"
}